ambition_labs/__init__.py
ambition_labs/aliquot_types.py
ambition_labs/apps.py
ambition_labs/lab_profiles.py
ambition_labs/labs.py
ambition_labs/list_data.py
ambition_labs/panels.py
ambition_labs/processing_profiles.py
ambition_labs/reportables.py
ambition_labs/urls.py
ambition_labs/wsgi.py
ambition_labs/tests/__init__.py
ambition_labs/tests/test_labs.py
ambition_labs/tests/test_reportables.py
ambition_labs-0.1.19.dist-info/AUTHORS
ambition_labs-0.1.19.dist-info/LICENSE
ambition_labs-0.1.19.dist-info/METADATA
ambition_labs-0.1.19.dist-info/WHEEL
ambition_labs-0.1.19.dist-info/top_level.txt
ambition_labs-0.1.19.dist-info/RECORD
